{
  "project_info": {
    "project_number": "340108464063",
    "project_id": "seminar-7a814",
    "storage_bucket": "seminar-7a814.appspot.com"
  },
  "client": [
    {
      "client_info": {
        "mobilesdk_app_id": "1:340108464063:android:dcb8dee0fa7132817e5b0a",
        "android_client_info": {
          "package_name": "com.example.myapplication"
        }
      },
      "oauth_client": [
        {
          "client_id": "340108464063-18rr2id3soone92olvtquon3ikbphpke.apps.googleusercontent.com",
          "client_type": 1,
          "android_info": {
            "package_name": "com.example.myapplication",
            "certificate_hash": "cfdfc6972bae1d4af2483770ccac492c713026bc"
          }
        },
        {
          "client_id": "340108464063-5i8btr304s9c5ob9fkibn2t03bgk9056.apps.googleusercontent.com",
          "client_type": 3
        }
      ],
      "api_key": [
        {
          "current_key": "AIzaSyBH0oTIITgx2S9atixPgM7lPj4gfuH6jiI"
        }
      ],
      "services": {
        "appinvite_service": {
          "other_platform_oauth_client": [
            {
              "client_id": "340108464063-5i8btr304s9c5ob9fkibn2t03bgk9056.apps.googleusercontent.com",
              "client_type": 3
            }
          ]
        }
      }
    }
  ],
  "configuration_version": "1"
}